smart_alpha/__init__.py
smart_alpha/smart_alpha.py
smart_alpha-0.0.1.dist-info/LICENSE
smart_alpha-0.0.1.dist-info/WHEEL
smart_alpha-0.0.1.dist-info/METADATA
smart_alpha-0.0.1.dist-info/RECORD
