Metadata-Version: 2.1
Name: smart-alpha
Version: 0.0.1
Summary: Top-level package for Smart Alpha.
Home-page: https://github.com/amazingvince/smart_alpha
License: Apache-2.0
Author: Vincent Haines
Author-email: amazingvince@gmail.com
Requires-Python: >=3.5,<4.0
Classifier: Development Status :: 2 - Pre-Alpha
Classifier: Intended Audience :: Developers
Classifier: License :: OSI Approved :: Apache Software License
Classifier: Natural Language :: English
Classifier: Programming Language :: Python :: 3
Classifier: Programming Language :: Python :: 3.5
Classifier: Programming Language :: Python :: 3.6
Classifier: Programming Language :: Python :: 3.7
Classifier: Programming Language :: Python :: 3.8
Classifier: Programming Language :: Python :: 3.9
